aitoolshed/__init__.py
aitoolshed-0.0.0.dist-info/METADATA
aitoolshed-0.0.0.dist-info/WHEEL
aitoolshed-0.0.0.dist-info/top_level.txt
aitoolshed-0.0.0.dist-info/RECORD
